odoo/addons/iot_amqp_oca/README.rst
odoo/addons/iot_amqp_oca/__init__.py
odoo/addons/iot_amqp_oca/__manifest__.py
odoo/addons/iot_amqp_oca/data/system_data.xml
odoo/addons/iot_amqp_oca/i18n/iot_amqp.pot
odoo/addons/iot_amqp_oca/i18n/iot_amqp_oca.pot
odoo/addons/iot_amqp_oca/i18n/it.po
odoo/addons/iot_amqp_oca/models/__init__.py
odoo/addons/iot_amqp_oca/models/iot_amqp_host.py
odoo/addons/iot_amqp_oca/models/iot_communication_system_action.py
odoo/addons/iot_amqp_oca/models/iot_device_output.py
odoo/addons/iot_amqp_oca/models/iot_device_output_action.py
odoo/addons/iot_amqp_oca/readme/CONTRIBUTORS.rst
odoo/addons/iot_amqp_oca/readme/DESCRIPTION.rst
odoo/addons/iot_amqp_oca/security/ir.model.access.csv
odoo/addons/iot_amqp_oca/static/description/icon.png
odoo/addons/iot_amqp_oca/static/description/index.html
odoo/addons/iot_amqp_oca/tests/__init__.py
odoo/addons/iot_amqp_oca/tests/test_amqp.py
odoo/addons/iot_amqp_oca/views/iot_amqp_host.xml
odoo/addons/iot_amqp_oca/views/iot_device_output_views.xml
odoo14_addon_iot_amqp_oca-14.0.1.0.1.dev9.dist-info/METADATA
odoo14_addon_iot_amqp_oca-14.0.1.0.1.dev9.dist-info/WHEEL
odoo14_addon_iot_amqp_oca-14.0.1.0.1.dev9.dist-info/top_level.txt
odoo14_addon_iot_amqp_oca-14.0.1.0.1.dev9.dist-info/RECORD
