Metadata-Version: 2.1
Name: odoo14-addon-iot-amqp-oca
Version: 14.0.1.0.1.dev9
Summary: Integrate Iot Outputs with AMQP
Home-page: https://github.com/OCA/iot
Author: Creu Blanca, Odoo Community Association (OCA)
Author-email: support@odoo-community.org
License: AGPL-3
Platform: UNKNOWN
Classifier: Programming Language :: Python
Classifier: Framework :: Odoo
Classifier: Framework :: Odoo :: 14.0
Classifier: License :: OSI Approved :: GNU Affero General Public License v3
Requires-Python: >=3.6
Requires-Dist: odoo14-addon-iot-output-oca
Requires-Dist: odoo <14.1dev,>=14.0a
Requires-Dist: pika
